lorem/__init__.py
printerbob-0.0.30.dist-info/METADATA
printerbob-0.0.30.dist-info/WHEEL
printerbob-0.0.30.dist-info/top_level.txt
printerbob-0.0.30.dist-info/RECORD
