Metadata-Version: 2.1
Name: printerbob
Version: 0.0.30
Summary: printerbob
Home-page: UNKNOWN
Author: printerbob
Author-email: bob-tester@temp-mail.cloud
License: GPLv3
Platform: UNKNOWN
Requires-Python: >=3.8
